{
  "feeds": {
    "taskmaster": {
      "last_checked_at": "2026-02-19T19:10:27+00:00",
      "last_checked_unix": 1771528229,
      "etag": "\"ce3df-64b1df7968ff9\"",
      "last_modified": "Wed, 18 Feb 2026 19:12:20 GMT"
    },
    "taskmaster-peoples": {
      "last_checked_at": "2026-02-19T19:10:27+00:00",
      "last_checked_unix": 1771528229,
      "etag": "\"1069a0-64af460fde0f4\"",
      "last_modified": "Mon, 16 Feb 2026 17:35:19 GMT"
    },
    "off-menu": {
      "last_checked_at": "2026-02-19T19:10:27+00:00",
      "last_checked_unix": 1771528229,
      "etag": "\"djEuMi4wOjE3NzEzODcyMzk4MjQ=\""
    },
    "parenting-hell": {
      "last_checked_at": "2026-02-19T19:10:27+00:00",
      "last_checked_unix": 1771528229,
      "last_modified": "Tue, 17 Feb 2026 16:39:55 GMT"
    },
    "films-to-be-buried-with": {
      "last_checked_at": "2026-02-19T19:10:27+00:00",
      "last_checked_unix": 1771528229,
      "last_modified": "Wed, 18 Feb 2026 08:29:00 GMT"
    },
    "adam-buxton": {
      "last_checked_at": "2026-02-19T19:10:27+00:00",
      "last_checked_unix": 1771528229,
      "etag": "\"djEuMi4wOjE3Njg2MzY0MjEyOTU=\""
    },
    "rhlstp": {
      "last_checked_at": "2026-02-19T19:10:27+00:00",
      "last_checked_unix": 1771528229,
      "etag": "\"djEuMi4wOjE3NzE1MDMwMTE5NzA=\""
    },
    "bugle": {
      "last_checked_at": "2026-02-19T19:10:27+00:00",
      "last_checked_unix": 1771528229,
      "etag": "\"djEuMi4wOjE3NzE0MjIwNjAzMzk=\""
    },
    "athletico-mince": {
      "last_checked_at": "2026-02-19T19:10:27+00:00",
      "last_checked_unix": 1771528229,
      "etag": "\"djEuMi4wOjE3NjY1ODc3MzExOTY=\""
    },
    "three-bean-salad": {
      "last_checked_at": "2026-02-19T19:10:27+00:00",
      "last_checked_unix": 1771528229,
      "etag": "\"9819d-64968e49e7a99\"",
      "last_modified": "Wed, 28 Jan 2026 01:45:21 GMT"
    },
    "no-such-thing-as-a-fish": {
      "last_checked_at": "2026-02-19T19:10:27+00:00",
      "last_checked_unix": 1771528229,
      "etag": "W/\"fa836cd5f26eb3cf1e0a5ce572afa949\"",
      "last_modified": "Thu, 19 Feb 2026 17:25:25 GMT"
    },
    "horne-section": {
      "last_checked_at": "2026-02-19T19:10:27+00:00",
      "last_checked_unix": 1771528229,
      "etag": "\"djEuMi4wOjE3NjgwNjczMjU5Mzg=\""
    },
    "shagged-married-annoyed": {
      "last_checked_at": "2026-02-19T19:10:27+00:00",
      "last_checked_unix": 1771528229,
      "last_modified": "Thu, 19 Feb 2026 11:14:08 GMT"
    },
    "elis-james-john-robins": {
      "last_checked_at": "2026-02-19T19:10:27+00:00",
      "last_checked_unix": 1771528257,
      "etag": "\"d5b82a4057bfee937a38c8694e53fd24\"",
      "last_modified": "Thu, 19 Feb 2026 15:28:10 GMT"
    },
    "budpod": {
      "last_checked_at": "2026-02-19T19:10:27+00:00",
      "last_checked_unix": 1771528262,
      "etag": "\"djEuMi4wOjE3NzEzOTQ1MDAxNjc=\""
    },
    "my-dad-wrote-a-porno": {
      "last_checked_at": "2026-02-19T19:10:27+00:00",
      "last_checked_unix": 1771528262,
      "etag": "\"djEuMi4wOjE3NjYyNDc1Mjg2MzQ=\""
    },
    "help-i-sexted-my-boss": {
      "last_checked_at": "2026-02-19T19:10:27+00:00",
      "last_checked_unix": 1771528262,
      "etag": "\"ZGpFdU1pNHdPakUzTnpFME9EQTRNemszTWpRPTo6c2F4ZXNz\""
    },
    "have-a-word": {
      "last_checked_at": "2026-02-19T19:10:27+00:00",
      "last_checked_unix": 1771528267,
      "etag": "\"djEuMi4wOjE3NzEyMDA2MzkyNzk=\""
    },
    "comedians-comedian": {
      "last_checked_at": "2026-02-19T19:10:27+00:00",
      "last_checked_unix": 1771528267,
      "etag": "\"djEuMi4wOjE3NzE0ODA4Mzk2NDY=\""
    },
    "guilty-feminist": {
      "last_checked_at": "2026-02-19T19:10:27+00:00",
      "last_checked_unix": 1771528277,
      "last_modified": "Tue, 17 Feb 2026 12:00:00 GMT"
    },
    "st-elwicks": {
      "last_checked_at": "2026-02-19T19:10:27+00:00",
      "last_checked_unix": 1771528277,
      "etag": "W/\"e604-sVLl9FpD4Y90o3/XKbqaQeWk+eg\""
    },
    "wolf-owl": {
      "last_checked_at": "2026-02-19T19:10:27+00:00",
      "last_checked_unix": 1771528277,
      "last_modified": "Fri, 16 Jan 2026 01:08:14 GMT"
    },
    "katherine-ryan": {
      "last_checked_at": "2026-02-19T19:10:27+00:00",
      "last_checked_unix": 1771528277,
      "etag": "\"djEuMi4wOjE3NzE0MDQ3NzYzMjM=\""
    },
    "matt-forde-political-party": {
      "last_checked_at": "2026-02-19T19:10:27+00:00",
      "last_checked_unix": 1771528278,
      "etag": "\"djEuMi4wOjE3NzEzNDYyOTg3NDg=\""
    },
    "frank-off-the-radio": {
      "last_checked_at": "2026-02-19T19:10:27+00:00",
      "last_checked_unix": 1771528278,
      "last_modified": "Thu, 19 Feb 2026 00:06:42 GMT"
    },
    "friday-night-comedy": {
      "last_checked_at": "2026-02-19T19:10:27+00:00",
      "last_checked_unix": 1771528278,
      "etag": "\"980bf4f2e5866ca1c66121a34401c0bd\"",
      "last_modified": "Thu, 19 Feb 2026 18:57:03 GMT"
    },
    "acquisitions-incorporated": {
      "last_checked_at": "2026-03-21T21:42:22+00:00",
      "last_checked_unix": 1774129343
    },
    "abraxas-precipice-the-expanse-roleplaying-game-actual-play": {
      "last_checked_at": "2026-03-21T21:42:22+00:00",
      "last_checked_unix": 1774129343,
      "etag": "\"4897032ceb742832ccad5ea8b88d2d53\""
    },
    "advantage-a-5e-dungeons-dragons-podcast": {
      "last_checked_at": "2026-03-21T21:42:22+00:00",
      "last_checked_unix": 1774129343,
      "consecutive_failures": 0
    },
    "aint-slayed-nobody-call-of-cthulhu-actual-play": {
      "last_checked_at": "2026-03-21T21:42:22+00:00",
      "last_checked_unix": 1774129343,
      "etag": "\"djEuMi4wOjE3NzI1Mzc0OTkzNTg=\""
    },
    "analog-science-fiction-fact": {
      "last_checked_at": "2026-03-21T21:42:22+00:00",
      "last_checked_unix": 1774129343,
      "etag": "\"4ab40082afef666d488362e21fd3ee25-gzip\"",
      "last_modified": "Sun, 08 Mar 2026 23:46:29 GMT"
    },
    "awful-neutral-a-dungeons-and-dragons-debacle": {
      "last_checked_at": "2026-03-21T21:42:22+00:00",
      "last_checked_unix": 1774129344,
      "etag": "\"05375ca20cd4ea0b5817fe133e3e4aff\""
    },
    "ballad-of-the-seven-dice-a-pathfinder-call-of-cthulhu-podcast": {
      "last_checked_at": "2026-03-21T21:42:22+00:00",
      "last_checked_unix": 1774129344,
      "etag": "\"45419607acdd273965524b197b470fcd\""
    },
    "bardic-mystery-tour-a-musical-dungeons-dragons-actualplay": {
      "last_checked_at": "2026-03-21T21:42:22+00:00",
      "last_checked_unix": 1774129344,
      "etag": "\"7cb2ac87dce2e6426c39022045df3ff7\""
    },
    "black-dice-society": {
      "last_checked_at": "2026-03-21T21:42:22+00:00",
      "last_checked_unix": 1774129344,
      "etag": "W/\"4a2aa-t8y4WbFF8scUOpFK0xAHibycIYo\""
    },
    "blood-of-the-void": {
      "last_checked_at": "2026-03-21T21:42:22+00:00",
      "last_checked_unix": 1774129344,
      "etag": "W/\"f0ae3a0f2e225fda806fe2a9a1575640\"",
      "last_modified": "Tue, 02 Dec 2025 22:32:05 GMT"
    },
    "bombarded-a-musical-dungeons-dragons-adventure": {
      "last_checked_at": "2026-03-21T21:42:22+00:00",
      "last_checked_unix": 1774129344,
      "etag": "\"2d8a93ebfb0dc004869bb40ed6be3cb2\""
    },
    "critical-role": {
      "last_checked_at": "2026-03-21T21:42:22+00:00",
      "last_checked_unix": 1774129344,
      "etag": "\"f77da2be3341d329653c1251e5e18c1a\"",
      "last_modified": "Tue, 17 Mar 2026 12:00:19 GMT"
    },
    "cosmic-crit-a-starfinder-actual-play-podcast": {
      "last_checked_at": "2026-03-21T21:42:22+00:00",
      "last_checked_unix": 1774129345,
      "last_modified": "Mon, 16 Mar 2026 04:05:00 GMT"
    },
    "curse-of-strahd-twice-bitten": {
      "last_checked_at": "2026-03-21T21:42:22+00:00",
      "last_checked_unix": 1774129344,
      "etag": "W/\"e91bf-cmzce1FK2wv0U8+6ZlOVdczLYOQ\""
    },
    "curse-of-strahdanya-a-legends-of-avantris-podcast": {
      "last_checked_at": "2026-03-21T21:42:22+00:00",
      "last_checked_unix": 1774129344,
      "etag": "\"41739a368c43334409dd1ab32db1ffab\""
    },
    "d-d-villains-of-visentria-a-grim-horror-themed-campaign": {
      "last_checked_at": "2026-03-21T21:42:22+00:00",
      "last_checked_unix": 1774129344,
      "etag": "W/\"c6fa-YOdBtj+xaJV9RckK4gGrf3zPP1U\""
    },
    "d20-dames": {
      "last_checked_at": "2026-03-21T21:42:22+00:00",
      "last_checked_unix": 1774129345,
      "etag": "\"504aca73587c1f685c29563b62d93d17\"",
      "last_modified": "Mon, 15 Dec 2025 06:28:56 GMT"
    },
    "die-alone-a-solo-rpg-podcast": {
      "last_checked_at": "2026-03-21T21:42:22+00:00",
      "last_checked_unix": 1774129345,
      "etag": "W/\"4d9ee438a267ef680a00ccf5a1f40c50\""
    },
    "diefall": {
      "last_checked_at": "2026-03-21T21:42:22+00:00",
      "last_checked_unix": 1774129346,
      "consecutive_failures": 0
    },
    "dimension-20": {
      "last_checked_at": "2026-03-21T21:42:22+00:00",
      "last_checked_unix": 1774129345,
      "etag": "\"d5595f2f83834d32e8fc04988b0483a7\"",
      "last_modified": "Mon, 16 Mar 2026 12:05:19 GMT"
    },
    "dungeons-and-daddies": {
      "last_checked_at": "2026-03-21T21:42:22+00:00",
      "last_checked_unix": 1774129345,
      "etag": "\"djEuMi4wOjE3NzM5NTg4NDQ0NzY=\""
    },
    "worlds-beyond-number": {
      "last_checked_at": "2026-03-21T21:42:22+00:00",
      "last_checked_unix": 1774129345,
      "etag": "\"472c75e02a44c87c1f15b2e68d4196c1\"",
      "last_modified": "Fri, 20 Mar 2026 19:54:30 GMT"
    },
    "dndark": {
      "last_checked_at": "2026-03-21T21:42:22+00:00",
      "last_checked_unix": 1774129346
    },
    "dodoborne-a-daggerheart-actual-play-podcast": {
      "last_checked_at": "2026-03-21T21:42:22+00:00",
      "last_checked_unix": 1774129345,
      "etag": "W/\"c5070b0dc7bfa563f17bdb85d73b5c18\"",
      "last_modified": "Sat, 21 Mar 2026 10:41:10 GMT"
    },
    "dragons-greed-gaming-presents-blade-runner-the-roleplaying-game": {
      "last_checked_at": "2026-03-21T21:42:22+00:00",
      "last_checked_unix": 1774129346,
      "etag": "\"c63c1b84e68c49bd553117a449b52571\"",
      "last_modified": "Mon, 16 Mar 2026 12:56:55 GMT"
    },
    "dork-tales": {
      "last_checked_at": "2026-03-21T21:42:22+00:00",
      "last_checked_unix": 1774129346,
      "etag": "\"ab1e656e21c0a912aa8971efa96e7418\""
    },
    "dragons-greed-gaming-presents-mork-borg": {
      "last_checked_at": "2026-03-21T21:42:22+00:00",
      "last_checked_unix": 1774129346,
      "etag": "\"d294356cc513f6c6fa973ac401655100\"",
      "last_modified": "Mon, 16 Mar 2026 12:49:02 GMT"
    },
    "dumbgeons-and-dragons-a-funny-rules-light-d-d-actual-play-podcast": {
      "last_checked_at": "2026-03-21T21:42:22+00:00",
      "last_checked_unix": 1774129347,
      "last_modified": "Wed, 18 Mar 2026 16:00:01 GMT"
    },
    "flail-to-the-face-a-compatible-with-m-rk-borg-actual-play-podcast": {
      "last_checked_at": "2026-03-21T21:42:22+00:00",
      "last_checked_unix": 1774129347,
      "etag": "W/\"62922-69kED1DwSyeCc8rxcwQIF+VLJAo\""
    },
    "fables-of-refuge": {
      "last_checked_at": "2026-03-21T21:42:22+00:00",
      "last_checked_unix": 1774129347,
      "etag": "W/\"61fe3-xXPcfFbf7JSQjf8SS0mJQHRU+X4\""
    },
    "force-majeure-a-star-wars-actual-play-podcast": {
      "last_checked_at": "2026-03-21T21:42:22+00:00",
      "last_checked_unix": 1774129348,
      "etag": "\"72ee780b355d3eb58cb8b79a059a9a40\"",
      "last_modified": "Tue, 17 Mar 2026 16:22:22 GMT"
    },
    "friends-at-the-table": {
      "last_checked_at": "2026-03-21T21:42:22+00:00",
      "last_checked_unix": 1774129348,
      "etag": "\"6e85d4674c59e8f632c4bb34dda994d1\"",
      "last_modified": "Fri, 20 Mar 2026 20:58:28 GMT"
    },
    "girls-guts-glory-the-broad-cast": {
      "last_checked_at": "2026-03-21T21:42:22+00:00",
      "last_checked_unix": 1774129348,
      "last_modified": "Sat, 21 Mar 2026 21:39:50 GMT"
    },
    "godfall-dnd": {
      "last_checked_at": "2026-03-21T21:42:22+00:00",
      "last_checked_unix": 1774129348,
      "etag": "W/\"46c4-RhpHjPaLMthPqxXHdTbjo6jLul4\""
    },
    "godsfall": {
      "last_checked_at": "2026-03-21T21:42:22+00:00",
      "last_checked_unix": 1774129348
    },
    "guildgates-goblins-a-dungeons-dragons-podcast": {
      "last_checked_at": "2026-02-20T10:00:00+00:00",
      "last_checked_unix": 1771581613,
      "consecutive_failures": 3,
      "last_error_at": "2026-02-20T10:00:00+00:00",
      "last_error_status": 404,
      "last_error_message": "Not Found",
      "disabled": true,
      "disabled_at": "2026-02-20T10:00:00+00:00",
      "disabled_url": "https://feed.podbean.com/guildgatesandgoblins/feed.xml",
      "disabled_reason": "3 consecutive failures"
    },
    "green-box-gaming": {
      "last_checked_at": "2026-03-21T21:42:22+00:00",
      "last_checked_unix": 1774129348,
      "etag": "\"761a9be631b11bff17aac8ce3e43cb5c\"",
      "last_modified": "Tue, 17 Mar 2026 16:06:43 GMT"
    },
    "greetings-adventurers-dungeons-and-dragons-5e-actual-play": {
      "last_checked_at": "2026-03-21T21:42:22+00:00",
      "last_checked_unix": 1774129348,
      "etag": "\"djEuMi4wOjE3NzM2NzY4Mzk0NzE=\""
    },
    "happy-jacks-rpg-one-shots": {
      "last_checked_at": "2026-03-21T21:42:22+00:00",
      "last_checked_unix": 1774129349,
      "etag": "\"76eacc076550ad8b38eae6e65125ddfc\"",
      "last_modified": "Wed, 18 Mar 2026 14:49:00 GMT",
      "consecutive_failures": 0
    },
    "hero-squad": {
      "last_checked_at": "2026-03-21T21:42:22+00:00",
      "last_checked_unix": 1774129348,
      "etag": "\"b9d8a43d7b16981b25899e156c5fcb19\""
    },
    "heroes-of-the-vale": {
      "last_checked_at": "2026-03-21T21:42:22+00:00",
      "last_checked_unix": 1774129348,
      "last_modified": "Sat, 21 Mar 2026 21:39:12 GMT"
    },
    "high-rollers-dnd": {
      "last_checked_at": "2026-03-21T21:42:22+00:00",
      "last_checked_unix": 1774129348,
      "last_modified": "Thu, 19 Mar 2026 08:07:43 GMT"
    },
    "how-we-roll-podcast": {
      "last_checked_at": "2026-03-21T21:42:22+00:00",
      "last_checked_unix": 1774129349,
      "etag": "\"a9ad4313007e43ceca678cf4a4e268fb\"",
      "last_modified": "Tue, 17 Mar 2026 10:19:21 GMT"
    },
    "how-friends-roll-a-dungeons-and-dragons-5th-edition-actual-play-dnd-5e-podcast": {
      "last_checked_at": "2026-03-21T21:42:22+00:00",
      "last_checked_unix": 1774129349,
      "etag": "\"d765ba6513325531959767c6fe05b93a\"",
      "last_modified": "Thu, 11 Dec 2025 02:12:00 GMT"
    },
    "lamplight-radio-play": {
      "last_checked_at": "2026-03-21T21:42:22+00:00",
      "last_checked_unix": 1774129350,
      "etag": "\"dae5fecbf2745352c65edbebadc303f0\"",
      "last_modified": "Mon, 17 Nov 2025 19:01:24 GMT",
      "consecutive_failures": 0
    },
    "lawful-stupid-a-dnd-5e-actual-play-podcast": {
      "last_checked_at": "2026-03-21T21:42:22+00:00",
      "last_checked_unix": 1774129349,
      "etag": "W/\"2eb03c-CJ/WJBO7/5Usj2ijzK7uXhGXl/g\""
    },
    "mythic-thunderlute-a-d-d-podcast-musical": {
      "last_checked_at": "2026-03-21T21:42:22+00:00",
      "last_checked_unix": 1774129349,
      "last_modified": "Sat, 06 Dec 2025 17:09:19 GMT"
    },
    "legendlark": {
      "last_checked_at": "2026-03-21T21:42:22+00:00",
      "last_checked_unix": 1774129349,
      "etag": "W/\"121c2f-BwnpnuTRl74ltp64XILxpqaksO4\"",
      "consecutive_failures": 0
    },
    "nerd-poker": {
      "last_checked_at": "2026-03-21T21:42:22+00:00",
      "last_checked_unix": 1774129350,
      "etag": "\"c85aa4c59656d021abe25a9b52fcd1e3\"",
      "last_modified": "Thu, 19 Mar 2026 00:12:32 GMT"
    },
    "not-another-d-d-podcast": {
      "last_checked_at": "2026-03-21T21:42:22+00:00",
      "last_checked_unix": 1774129350,
      "last_modified": "Fri, 20 Mar 2026 02:25:56 GMT"
    },
    "one-shot": {
      "last_checked_at": "2026-03-21T21:42:22+00:00",
      "last_checked_unix": 1774129350,
      "last_modified": "Wed, 18 Mar 2026 04:37:47 GMT"
    },
    "one-shots-a-live-play-mini-series-podcast": {
      "last_checked_at": "2026-03-21T21:42:22+00:00",
      "last_checked_unix": 1774129351,
      "etag": "\"9814d02e38a135d6b7589f746046c864\"",
      "last_modified": "Mon, 02 Mar 2026 20:53:47 GMT"
    },
    "one-shot-onslaught-a-d-d-5e-actual-play-podcast": {
      "last_checked_at": "2026-03-21T21:42:22+00:00",
      "last_checked_unix": 1774129350,
      "last_modified": "Tue, 03 Mar 2026 18:54:32 GMT"
    },
    "order-of-shana-the-women-running-dungeon-crawl-classics-rpg": {
      "last_checked_at": "2026-03-21T21:42:22+00:00",
      "last_checked_unix": 1774129350,
      "etag": "W/\"a2da-v8yjnkd4B2qu0G7dgpi+eK+8NO8\""
    },
    "oxventure-a-dungeons-dragons-podcast": {
      "last_checked_at": "2026-03-21T21:42:22+00:00",
      "last_checked_unix": 1774129351,
      "last_modified": "Mon, 02 Mar 2026 20:46:54 GMT"
    },
    "archives-fandible-actual-play-podcast": {
      "last_checked_at": "2026-03-21T21:42:22+00:00",
      "last_checked_unix": 1774129351,
      "etag": "\"43ff6354ce54aee5a69f209386f2c167\"",
      "consecutive_failures": 0
    },
    "realms-of-peril-glory-an-actual-play-anthology": {
      "last_checked_at": "2026-03-21T21:42:22+00:00",
      "last_checked_unix": 1774129351,
      "last_modified": "Fri, 20 Mar 2026 23:08:27 GMT"
    },
    "realmsmith-presents-into-the-mist-live-dnd-podcast": {
      "last_checked_at": "2026-03-21T21:42:22+00:00",
      "last_checked_unix": 1774129351,
      "etag": "W/\"1f64a-bmEENEneh+U3scKUhX2+s6z+CQc\""
    },
    "rime-of-the-frostmaiden-a-d-d5e-actual-play-adventure": {
      "last_checked_at": "2026-03-21T21:42:22+00:00",
      "last_checked_unix": 1774129352,
      "etag": "\"6cc173bef1bec6c59e3ab5b995bd6043\"",
      "last_modified": "Mon, 16 Mar 2026 12:36:34 GMT",
      "consecutive_failures": 0
    },
    "role-radio-a-5e-actual-play-dungeons-dragons-podcast": {
      "last_checked_at": "2026-03-21T21:42:22+00:00",
      "last_checked_unix": 1774129351
    },
    "roll-britannia-a-british-dungeons-dragons-5e-podcast": {
      "last_checked_at": "2026-03-21T21:42:22+00:00",
      "last_checked_unix": 1774129351,
      "etag": "\"djEuMi4wOjE3NzM4MjE0MzkzMzM=\""
    },
    "roll-the-hard-20-podcast": {
      "last_checked_at": "2026-03-21T21:42:22+00:00",
      "last_checked_unix": 1774129352,
      "etag": "W/\"9617affdabece8dda9e1703fd0483413\""
    },
    "rotating-heroes": {
      "last_checked_at": "2026-03-21T21:42:22+00:00",
      "last_checked_unix": 1774129352,
      "etag": "W/\"d218a2021e0b858c3ab3162ef3a1a6a1\"",
      "last_modified": "Fri, 20 Mar 2026 10:00:00 GMT"
    },
    "session-zero": {
      "last_checked_at": "2026-03-21T21:42:22+00:00",
      "last_checked_unix": 1774129352,
      "last_modified": "Mon, 01 Jul 2024 21:16:57 GMT"
    },
    "star-trek-the-section-31-files-by-eric-l-busby": {
      "last_checked_at": "2026-02-20T10:00:00+00:00",
      "last_checked_unix": 1771581620,
      "consecutive_failures": 3,
      "last_error_at": "2026-02-20T10:00:00+00:00",
      "last_error_status": 404,
      "last_error_message": "Not Found",
      "disabled": true,
      "disabled_at": "2026-02-20T10:00:00+00:00",
      "disabled_url": "http://www.loyalbooks.com/book/Star-Trek-Section-31-Files/feed",
      "disabled_reason": "3 consecutive failures"
    },
    "sitcomd-d": {
      "last_checked_at": "2026-03-21T21:42:22+00:00",
      "last_checked_unix": 1774129352,
      "last_modified": "Wed, 22 Oct 2025 00:21:03 GMT"
    },
    "star-trek-europa-star-trek-adventures-actual-play": {
      "last_checked_at": "2026-03-21T21:42:22+00:00",
      "last_checked_unix": 1774129352,
      "etag": "\"8fddf08242aaa66a781bad691de27bae\""
    },
    "stars-are-right-call-of-cthulhu-ttrpg-actual-play-podcast": {
      "last_checked_at": "2026-03-21T21:42:22+00:00",
      "last_checked_unix": 1774129352,
      "etag": "\"b87c018725515ce978bb331d96e3ec1b\""
    },
    "strange-encounter-a-pirate-borg-actual-play": {
      "last_checked_at": "2026-03-21T21:42:22+00:00",
      "last_checked_unix": 1774129352,
      "etag": "\"djEuMi4wOjE3NjA2OTM0ODc3NjA=\""
    },
    "storybreakers": {
      "last_checked_at": "2026-03-21T21:42:22+00:00",
      "last_checked_unix": 1774129352,
      "last_modified": "Wed, 26 Jun 2024 21:02:13 GMT"
    },
    "tabletop-tiddies": {
      "last_checked_at": "2026-03-21T21:42:22+00:00",
      "last_checked_unix": 1774129352,
      "etag": "\"5e30c3040c1be0bb4e52de06af294166\"",
      "last_modified": "Sat, 21 Mar 2026 18:52:04 GMT"
    },
    "tales-from-the-stinky-dragon": {
      "last_checked_at": "2026-03-21T21:42:22+00:00",
      "last_checked_unix": 1774129352,
      "last_modified": "Wed, 18 Mar 2026 08:00:00 GMT"
    },
    "taking-initiative": {
      "last_checked_at": "2026-03-21T21:42:22+00:00",
      "last_checked_unix": 1774129352,
      "etag": "\"0ad5bb6791aa7f499fd65c1c96ad546b\"",
      "last_modified": "Mon, 15 Dec 2025 06:30:36 GMT"
    },
    "the-adventure-zone": {
      "last_checked_at": "2026-03-21T21:42:22+00:00",
      "last_checked_unix": 1774129352,
      "etag": "\"e0e902acd8cec083e8f3c8de650dbddc\"",
      "last_modified": "Thu, 19 Mar 2026 11:00:18 GMT"
    },
    "adventure-is-nigh": {
      "last_checked_at": "2026-03-21T21:42:22+00:00",
      "last_checked_unix": 1774129352,
      "etag": "W/\"18a71-Fuhb3cADV/34jy2QP3Hf5BRFyos\""
    },
    "the-adventures-of-philip-marlowe": {
      "last_checked_at": "2026-03-21T21:42:22+00:00",
      "last_checked_unix": 1774129353,
      "etag": "\"185c37e7e158b1bc1f0c187267cbda9a\"",
      "last_modified": "Mon, 16 Mar 2026 12:44:31 GMT"
    },
    "the-city-that-never-dies": {
      "last_checked_at": "2026-03-21T21:42:22+00:00",
      "last_checked_unix": 1774129352,
      "etag": "\"925b8edf1c8a5ff3bd93aa801410c09f\"",
      "last_modified": "Tue, 26 Dec 2023 11:00:14 GMT"
    },
    "the-damage-guild-a-d-d-podcast": {
      "last_checked_at": "2026-03-21T21:42:22+00:00",
      "last_checked_unix": 1774129353,
      "last_modified": "Mon, 16 Mar 2026 04:01:00 GMT",
      "consecutive_failures": 0
    },
    "the-damage-guild-a-pathfinder-2e-podcast": {
      "last_checked_at": "2026-03-21T21:42:22+00:00",
      "last_checked_unix": 1774129353,
      "last_modified": "Mon, 16 Mar 2026 04:01:00 GMT",
      "consecutive_failures": 0
    },
    "the-dice-girls": {
      "last_checked_at": "2026-03-21T21:42:22+00:00",
      "last_checked_unix": 1774129353,
      "etag": "\"2a0e269623e2ac38498fd7bc2b7c810e\""
    },
    "the-gilded-troll": {
      "last_checked_at": "2026-03-21T21:42:22+00:00",
      "last_checked_unix": 1774129353,
      "etag": "W/\"49394-aaSVZQ2YrNmcmzaiEjkSEuS5UKM\""
    },
    "the-glass-cannon-podcast": {
      "last_checked_at": "2026-03-21T21:42:22+00:00",
      "last_checked_unix": 1774129353,
      "last_modified": "Fri, 20 Mar 2026 04:00:00 GMT"
    },
    "the-heresies-of-radulf-burntwine": {
      "last_checked_at": "2026-03-21T21:42:22+00:00",
      "last_checked_unix": 1774129353,
      "last_modified": "Thu, 26 Feb 2026 18:03:09 GMT"
    },
    "the-iron-realm-mega-dungeon-crawl-dark-fantasy-solo-rpg-gaming-podcast": {
      "last_checked_at": "2026-03-21T21:42:22+00:00",
      "last_checked_unix": 1774129353,
      "last_modified": "Mon, 9 Mar 2026 20:20:33 GMT"
    },
    "the-lovecraft-tapes-actual-play-call-of-cthulhu-podcast": {
      "last_checked_at": "2026-03-21T21:42:22+00:00",
      "last_checked_unix": 1774129353,
      "etag": "\"6483899e15d7c8b500f854ff049dd718\""
    },
    "the-magpies-a-blades-in-the-dark-actual-play": {
      "last_checked_at": "2026-03-21T21:42:22+00:00",
      "last_checked_unix": 1774129353,
      "etag": "\"29cb0c0cd1c6e7275952cf89d252408d\"",
      "last_modified": "Mon, 07 Feb 2022 11:00:14 GMT"
    },
    "the-misadventurers-a-d-d-folklore-mystery-tour": {
      "last_checked_at": "2026-03-21T21:42:22+00:00",
      "last_checked_unix": 1774129353,
      "consecutive_failures": 0
    },
    "mystery-quest": {
      "last_checked_at": "2026-03-21T21:42:22+00:00",
      "last_checked_unix": 1774129353,
      "last_modified": "Fri, 20 Mar 2026 17:07:40 GMT"
    },
    "natural-six": {
      "last_checked_at": "2026-03-21T21:42:22+00:00",
      "last_checked_unix": 1774129354,
      "etag": "\"djEuMi4wOjE3NzM3Nzc2Mzk1MTQ=\""
    },
    "the-apocalypse-players": {
      "last_checked_at": "2026-03-21T21:42:22+00:00",
      "last_checked_unix": 1774129354,
      "etag": "\"75e0692b05cd18a719a07df19283cb38\""
    },
    "the-otherplace-an-actual-play-rpg-podcast": {
      "last_checked_at": "2026-03-21T21:42:22+00:00",
      "last_checked_unix": 1774129354,
      "etag": "W/\"5b75f-H3aYnvM7sifxS9q9mOv28C+ZxZQ\""
    },
    "the-rpgeeks": {
      "last_checked_at": "2026-03-21T21:42:22+00:00",
      "last_checked_unix": 1774129354,
      "etag": "\"394adaa6a7e99cbb80bc3579c2f4befa\""
    },
    "the-tabletop-tales": {
      "last_checked_at": "2026-03-21T21:42:22+00:00",
      "last_checked_unix": 1774129354,
      "etag": "\"991d6898abf62da0baad81f35d5d3e19\"",
      "last_modified": "Sat, 14 Mar 2026 13:30:40 GMT"
    },
    "the-unexpectables": {
      "last_checked_at": "2026-03-21T21:42:22+00:00",
      "last_checked_unix": 1774129354,
      "etag": "\"e66795f9da8279176880a671ee32e32a\"",
      "last_modified": "Fri, 27 Feb 2026 17:40:16 GMT"
    },
    "the-vintage-rpg-podcast": {
      "last_checked_at": "2026-03-21T21:42:22+00:00",
      "last_checked_unix": 1774129354,
      "etag": "\"728065374d9aabb6e1d079943c58a31b\"",
      "last_modified": "Fri, 20 Mar 2026 21:38:22 GMT"
    },
    "time-for-chaos-a-call-of-cthulhu-masks-of-nyarlathotep-campaign": {
      "last_checked_at": "2026-03-21T21:42:22+00:00",
      "last_checked_unix": 1774129354,
      "etag": "\"djEuMi4wOjE3MjUwNzY4ODc2OTU=\""
    },
    "tomes-tentacles-call-of-cthulhu-actual-play": {
      "last_checked_at": "2026-03-21T21:42:22+00:00",
      "last_checked_unix": 1774129354,
      "etag": "\"9768bbd24a59f0aa598cc843f5c59e83\"",
      "last_modified": "Mon, 15 Dec 2025 06:31:32 GMT"
    },
    "twilight-zone-radio-dramas": {
      "last_checked_at": "2026-03-21T21:42:22+00:00",
      "last_checked_unix": 1774129373,
      "etag": "\"61daffee-19969\"",
      "last_modified": "Sun, 09 Jan 2022 15:31:58 GMT",
      "consecutive_failures": 0
    },
    "we-fix-space-junk": {
      "last_checked_at": "2026-03-21T21:42:22+00:00",
      "last_checked_unix": 1774129354,
      "last_modified": "Fri, 13 Mar 2026 17:24:46 GMT"
    },
    "who-lives-who-dice": {
      "last_checked_at": "2026-03-21T21:42:22+00:00",
      "last_checked_unix": 1774129355,
      "etag": "\"d0a9d9a8995f264b5f6e5e9e8be1f4bb\"",
      "last_modified": "Tue, 17 Mar 2026 22:53:19 GMT"
    },
    "viva-la-dirt-league-d-d": {
      "last_checked_at": "2026-03-21T21:42:22+00:00",
      "last_checked_unix": 1774129355,
      "last_modified": "Thu, 05 Feb 2026 18:33:12 GMT",
      "etag": "W/\"b031b-4s2wxBU62kRuStbBi2y8KxRfD8A\""
    }
  },
  "updated_at": "2026-03-21T21:42:22+00:00"
}
